{"Sunderland : West Ham": {"date": "Sat, 15-04-17", "home": "Sunderland", "away": "West Ham", "list": {"home": {"possession": "47.6", "ratings": "6.60", "aerials_won": "10", "corners": "6", "pass_success": "78", "tackles": "17", "dribbles": "7", "shots": "14", "dispossessed": "8"}, "away": {"possession": "52.4", "ratings": "6.57", "aerials_won": "14", "corners": "1", "pass_success": "77", "tackles": "12", "dribbles": "9", "shots": "7", "dispossessed": "12"}}, "result": "2 : 2"}, "Middlesbrough : Sunderland": {"date": "Wed, 26-04-17", "home": "Middlesbrough", "away": "Sunderland", "list": {"home": {"possession": "48.9", "ratings": "6.93", "aerials_won": "28", "corners": "3", "pass_success": "71", "tackles": "13", "dribbles": "5", "shots": "6", "dispossessed": "12"}, "away": {"possession": "51.1", "ratings": "6.66", "aerials_won": "39", "corners": "5", "pass_success": "73", "tackles": "15", "dribbles": "9", "shots": "10", "dispossessed": "9"}}, "result": "1 : 0"}, "Leicester : Sunderland": {"date": "Tue, 04-04-17", "home": "Leicester", "away": "Sunderland", "list": {"home": {"possession": "54.7", "ratings": "7.20", "dispossessed": "14", "corners": "5", "pass_success": "78", "tackles": "11", "dribbles": "4", "shots": "19", "aerials_won": "23"}, "away": {"possession": "45.3", "ratings": "6.51", "dispossessed": "9", "corners": "6", "pass_success": "68", "tackles": "18", "dribbles": "2", "shots": "15", "aerials_won": "24"}}, "result": "2 : 0"}, "Sunderland : Man Utd": {"date": "Sun, 09-04-17", "home": "Sunderland", "away": "Man Utd", "list": {"home": {"possession": "29.7", "ratings": "6.40", "aerials_won": "12", "corners": "4", "pass_success": "67", "tackles": "16", "dribbles": "11", "shots": "9", "dispossessed": "9"}, "away": {"possession": "70.3", "ratings": "7.42", "aerials_won": "19", "corners": "5", "pass_success": "87", "tackles": "11", "dribbles": "12", "shots": "18", "dispossessed": "12"}}, "result": "0 : 3"}, "Arsenal : Sunderland": {"date": "Tue, 16-May-17", "home": "Arsenal", "away": "Sunderland", "list": {"home": {"possession": "62.5", "ratings": "7.37", "aerials_won": "18", "corners": "17", "pass_success": "88", "tackles": "9", "dribbles": "9", "shots": "36", "dispossessed": "12"}, "away": {"possession": "37.5", "ratings": "6.60", "aerials_won": "7", "corners": "3", "pass_success": "75", "tackles": "15", "dribbles": "9", "shots": "6", "dispossessed": "5"}}, "result": "2 : 0"}, "Hull : Sunderland": {"date": "Sat, 06-05-17", "home": "Hull", "away": "Sunderland", "list": {"home": {"possession": "59.5", "ratings": "6.26", "dispossessed": "13", "corners": "7", "pass_success": "79", "tackles": "13", "dribbles": "4", "shots": "16", "aerials_won": "8"}, "away": {"possession": "40.5", "ratings": "7.61", "dispossessed": "7", "corners": "4", "pass_success": "69", "tackles": "16", "dribbles": "10", "shots": "12", "aerials_won": "20"}}, "result": "0 : 2"}, "Sunderland : Swansea": {"date": "Sat, 13-05-17", "home": "Sunderland", "away": "Swansea", "list": {"home": {"possession": "52.8", "ratings": "6.26", "aerials_won": "9", "corners": "8", "pass_success": "83", "tackles": "21", "dribbles": "8", "shots": "13", "dispossessed": "13"}, "away": {"possession": "47.2", "ratings": "7.00", "aerials_won": "16", "corners": "4", "pass_success": "81", "tackles": "17", "dribbles": "2", "shots": "3", "dispossessed": "15"}}, "result": "0 : 2"}, "Chelsea : Sunderland": {"date": "Sun, 21-May-17", "home": "Chelsea", "away": "Sunderland", "list": {"home": {"possession": "70.5", "ratings": "7.42", "dispossessed": "15", "corners": "11", "pass_success": "91", "tackles": "16", "dribbles": "12", "shots": "28", "aerials_won": "10"}, "away": {"possession": "29.5", "ratings": "6.04", "dispossessed": "12", "corners": "1", "pass_success": "78", "tackles": "17", "dribbles": "9", "shots": "7", "aerials_won": "5"}}, "result": "5 : 1"}, "Sunderland : Bournemouth": {"date": "Sat, 29-04-17", "home": "Sunderland", "away": "Bournemouth", "list": {"home": {"possession": "40.9", "ratings": "6.81", "dispossessed": "12", "corners": "6", "pass_success": "75", "tackles": "27", "dribbles": "8", "shots": "17", "aerials_won": "20"}, "away": {"possession": "59.1", "ratings": "7.09", "dispossessed": "17", "corners": "5", "pass_success": "83", "tackles": "15", "dribbles": "9", "shots": "15", "aerials_won": "16"}}, "result": "0 : 1"}, "Watford : Sunderland": {"date": "Sat, 01-04-17", "home": "Watford", "away": "Sunderland", "list": {"home": {"possession": "56.7", "ratings": "7.32", "dispossessed": "4", "corners": "13", "pass_success": "82", "tackles": "19", "dribbles": "8", "shots": "23", "aerials_won": "28"}, "away": {"possession": "43.3", "ratings": "6.59", "dispossessed": "10", "corners": "9", "pass_success": "69", "tackles": "9", "dribbles": "3", "shots": "11", "aerials_won": "23"}}, "result": "1 : 0"}, "Sunderland : Burnley": {"date": "Sat, 18-03-17", "home": "Sunderland", "away": "Burnley", "list": {"home": {"possession": "44", "ratings": "6.90", "aerials_won": "24", "corners": "3", "pass_success": "63", "tackles": "15", "dribbles": "4", "shots": "14", "dispossessed": "5"}, "away": {"possession": "56", "ratings": "6.96", "aerials_won": "31", "corners": "5", "pass_success": "71", "tackles": "9", "dribbles": "7", "shots": "16", "dispossessed": "9"}}, "result": "0 : 0"}, "Sunderland : Man City": {"date": "Sun, 05-03-17", "home": "Sunderland", "away": "Man City", "list": {"home": {"possession": "29.2", "ratings": "6.47", "dispossessed": "13", "corners": "6", "pass_success": "70", "tackles": "25", "dribbles": "10", "shots": "11", "aerials_won": "9"}, "away": {"possession": "70.8", "ratings": "7.27", "dispossessed": "15", "corners": "4", "pass_success": "89", "tackles": "15", "dribbles": "9", "shots": "14", "aerials_won": "13"}}, "result": "0 : 2"}}